{ "height":200,
 "layers":[
        {
         "height":200,
         "name":"Meta",
         "objects":[
                {
                 "height":0,
                 "name":"",
                 "polyline":[
                        {
                         "x":267,
                         "y":-61
                        }, 
                        {
                         "x":824,
                         "y":103
                        }, 
                        {
                         "x":776,
                         "y":1248
                        }, 
                        {
                         "x":70,
                         "y":1600
                        }, 
                        {
                         "x":6,
                         "y":706
                        }],
                 "properties":
                    {

                    },
                 "type":"PlanningNodes",
                 "width":0,
                 "x":3596,
                 "y":658
                }, 
                {
                 "height":0,
                 "name":"",
                 "polyline":[
                        {
                         "x":6,
                         "y":136
                        }, 
                        {
                         "x":-1176,
                         "y":9
                        }, 
                        {
                         "x":-1003,
                         "y":-1215
                        }, 
                        {
                         "x":170,
                         "y":-1597
                        }, 
                        {
                         "x":597,
                         "y":-1261
                        }, 
                        {
                         "x":236,
                         "y":-891
                        }, 
                        {
                         "x":297,
                         "y":-573
                        }],
                 "properties":
                    {

                    },
                 "type":"PlanningNodes",
                 "width":0,
                 "x":2577,
                 "y":2186
                }, 
                {
                 "height":327,
                 "name":"guardArea1",
                 "properties":
                    {

                    },
                 "type":"GuardArea",
                 "width":761,
                 "x":3311,
                 "y":528
                }, 
                {
                 "height":327,
                 "name":"guardArea2",
                 "properties":
                    {

                    },
                 "type":"GuardArea",
                 "width":761,
                 "x":3965,
                 "y":1728
                }, 
                {
                 "height":327,
                 "name":"guardArea3",
                 "properties":
                    {

                    },
                 "type":"GuardArea",
                 "width":761,
                 "x":1220,
                 "y":1949
                }, 
                {
                 "height":327,
                 "name":"guardArea4",
                 "properties":
                    {

                    },
                 "type":"GuardArea",
                 "width":761,
                 "x":1229,
                 "y":795
                }, 
                {
                 "height":0,
                 "name":"",
                 "polyline":[
                        {
                         "x":-128,
                         "y":0
                        }, 
                        {
                         "x":-98,
                         "y":54
                        }, 
                        {
                         "x":19,
                         "y":77
                        }, 
                        {
                         "x":10,
                         "y":101
                        }, 
                        {
                         "x":-29,
                         "y":93
                        }, 
                        {
                         "x":4,
                         "y":124
                        }, 
                        {
                         "x":63,
                         "y":104
                        }, 
                        {
                         "x":64,
                         "y":32
                        }, 
                        {
                         "x":-32,
                         "y":0
                        }, 
                        {
                         "x":-128,
                         "y":0
                        }],
                 "properties":
                    {

                    },
                 "type":"Dynamic",
                 "width":0,
                 "x":2314,
                 "y":611
                }, 
                {
                 "height":0,
                 "name":"",
                 "polyline":[
                        {
                         "x":0,
                         "y":0
                        }, 
                        {
                         "x":1696,
                         "y":32
                        }],
                 "properties":
                    {
                     "amp1":"12"
                    },
                 "type":"Ground",
                 "width":0,
                 "x":1328,
                 "y":3184
                }, 
                {
                 "height":64,
                 "name":"",
                 "properties":
                    {
                     "name":"healthPickupRespawn1"
                    },
                 "type":"Pickup",
                 "width":70,
                 "x":3016,
                 "y":1000
                }, 
                {
                 "height":64,
                 "name":"",
                 "properties":
                    {
                     "name":"healthPickup1"
                    },
                 "type":"Pickup",
                 "width":70,
                 "x":1878,
                 "y":1222
                }, 
                {
                 "height":64,
                 "name":"",
                 "properties":
                    {
                     "name":"shieldBoost1"
                    },
                 "type":"Pickup",
                 "width":70,
                 "x":2378,
                 "y":1210
                }, 
                {
                 "height":64,
                 "name":"",
                 "properties":
                    {
                     "name":"scoreBonus1"
                    },
                 "type":"Pickup",
                 "width":70,
                 "x":2450,
                 "y":646
                }, 
                {
                 "height":64,
                 "name":"",
                 "properties":
                    {
                     "name":"hullBoost1"
                    },
                 "type":"Pickup",
                 "width":70,
                 "x":3248,
                 "y":1583
                }, 
                {
                 "height":64,
                 "name":"",
                 "properties":
                    {
                     "name":"scoreBonus1"
                    },
                 "type":"Pickup",
                 "width":70,
                 "x":4422,
                 "y":3184
                }, 
                {
                 "height":64,
                 "name":"",
                 "properties":
                    {
                     "name":"energyPickup1"
                    },
                 "type":"Pickup",
                 "width":70,
                 "x":3706,
                 "y":2938
                }, 
                {
                 "height":64,
                 "name":"",
                 "properties":
                    {
                     "name":"energyPickup1"
                    },
                 "type":"Pickup",
                 "width":70,
                 "x":1450,
                 "y":1164
                }, 
                {
                 "height":64,
                 "name":"",
                 "properties":
                    {
                     "name":"energyPickupRespawn1"
                    },
                 "type":"Pickup",
                 "width":70,
                 "x":2126,
                 "y":1560
                }, 
                {
                 "height":0,
                 "name":"dir",
                 "polyline":[
                        {
                         "x":0,
                         "y":0
                        }, 
                        {
                         "x":-182,
                         "y":142
                        }],
                 "properties":
                    {

                    },
                 "type":"Direction",
                 "width":0,
                 "x":4888,
                 "y":2294
                }, 
                {
                 "height":64,
                 "name":"",
                 "properties":
                    {
                     "name":"cannonBoost1"
                    },
                 "type":"Pickup",
                 "width":70,
                 "x":2415,
                 "y":2078
                }, 
                {
                 "height":64,
                 "name":"",
                 "properties":
                    {
                     "name":"grenadeLauncherBoost1"
                    },
                 "type":"Pickup",
                 "width":70,
                 "x":2876,
                 "y":2096
                }, 
                {
                 "height":64,
                 "name":"",
                 "properties":
                    {
                     "name":"maxEnergyBoost1"
                    },
                 "type":"Pickup",
                 "width":70,
                 "x":4505,
                 "y":2524
                }, 
                {
                 "height":64,
                 "name":"",
                 "properties":
                    {
                     "name":"missileLauncherBoost1"
                    },
                 "type":"Pickup",
                 "width":70,
                 "x":3670,
                 "y":1842
                }, 
                {
                 "height":64,
                 "name":"",
                 "properties":
                    {
                     "name":"repairBoost1"
                    },
                 "type":"Pickup",
                 "width":70,
                 "x":3952,
                 "y":2500
                }, 
                {
                 "height":64,
                 "name":"",
                 "properties":
                    {
                     "name":"infiniteEnergyBoost"
                    },
                 "type":"Pickup",
                 "width":70,
                 "x":4873,
                 "y":2640
                }, 
                {
                 "height":64,
                 "name":"",
                 "properties":
                    {
                     "name":"beamLaserBoost1"
                    },
                 "type":"Pickup",
                 "width":70,
                 "x":1565,
                 "y":1730
                }, 
                {
                 "height":64,
                 "name":"",
                 "properties":
                    {
                     "name":"energyRefillBoost1"
                    },
                 "type":"Pickup",
                 "width":70,
                 "x":4222,
                 "y":2428
                }, 
                {
                 "height":64,
                 "name":"",
                 "properties":
                    {
                     "name":"infiniteHullBoost"
                    },
                 "type":"Pickup",
                 "width":70,
                 "x":5077,
                 "y":2752
                }, 
                {
                 "height":64,
                 "name":"",
                 "properties":
                    {
                     "name":"turretBoost1"
                    },
                 "type":"Pickup",
                 "width":70,
                 "x":4322,
                 "y":2112
                }, 
                {
                 "height":64,
                 "name":"",
                 "properties":
                    {
                     "name":"engineBoost1"
                    },
                 "type":"Pickup",
                 "width":70,
                 "x":5277,
                 "y":2936
                }, 
                {
                 "height":64,
                 "name":"",
                 "properties":
                    {
                     "action":"levelComplete",
                     "actionMessage":"FANTASTIC!",
                     "actionMessageScale":"3",
                     "actionMessageType":"screen",
                     "active":"true",
                     "checkPeriod":"31",
                     "deactiveAfterExecute":"true",
                     "event":"allEnemiesDestroyed"
                    },
                 "type":"Reaction",
                 "width":64,
                 "x":2064,
                 "y":299
                }],
         "opacity":1,
         "type":"objectgroup",
         "visible":true,
         "width":200,
         "x":0,
         "y":0
        }, 
        {
         "height":200,
         "name":"Meta 2",
         "objects":[
                {
                 "height":1146,
                 "name":"guardArea5",
                 "properties":
                    {

                    },
                 "type":"GuardArea",
                 "width":1040,
                 "x":4814,
                 "y":449
                }, 
                {
                 "height":0,
                 "name":"",
                 "polyline":[
                        {
                         "x":0,
                         "y":0
                        }, 
                        {
                         "x":-1672,
                         "y":832
                        }, 
                        {
                         "x":-1616,
                         "y":2224
                        }, 
                        {
                         "x":632,
                         "y":2384
                        }, 
                        {
                         "x":2304,
                         "y":1176
                        }, 
                        {
                         "x":2144,
                         "y":312
                        }, 
                        {
                         "x":624,
                         "y":72
                        }],
                 "properties":
                    {
                     "graph":"big"
                    },
                 "type":"PlanningNodes",
                 "width":0,
                 "x":2781,
                 "y":235
                }, 
                {
                 "height":0,
                 "name":"",
                 "polyline":[
                        {
                         "x":0,
                         "y":0
                        }, 
                        {
                         "x":-336,
                         "y":-124
                        }, 
                        {
                         "x":-644,
                         "y":140
                        }, 
                        {
                         "x":-728,
                         "y":464
                        }, 
                        {
                         "x":-476,
                         "y":1020
                        }, 
                        {
                         "x":116,
                         "y":1376
                        }, 
                        {
                         "x":556,
                         "y":1360
                        }, 
                        {
                         "x":732,
                         "y":976
                        }, 
                        {
                         "x":744,
                         "y":412
                        }, 
                        {
                         "x":464,
                         "y":148
                        }, 
                        {
                         "x":200,
                         "y":128
                        }, 
                        {
                         "x":336,
                         "y":280
                        }, 
                        {
                         "x":490,
                         "y":396
                        }, 
                        {
                         "x":558,
                         "y":686
                        }, 
                        {
                         "x":462,
                         "y":1118
                        }, 
                        {
                         "x":100,
                         "y":1190
                        }, 
                        {
                         "x":-304,
                         "y":972
                        }, 
                        {
                         "x":-510,
                         "y":600
                        }, 
                        {
                         "x":-496,
                         "y":332
                        }, 
                        {
                         "x":-256,
                         "y":216
                        }, 
                        {
                         "x":-28,
                         "y":420
                        }, 
                        {
                         "x":164,
                         "y":592
                        }, 
                        {
                         "x":188,
                         "y":732
                        }, 
                        {
                         "x":26,
                         "y":784
                        }, 
                        {
                         "x":-92,
                         "y":670
                        }, 
                        {
                         "x":-240,
                         "y":582
                        }, 
                        {
                         "x":-220,
                         "y":710
                        }, 
                        {
                         "x":28,
                         "y":866
                        }, 
                        {
                         "x":228,
                         "y":836
                        }, 
                        {
                         "x":296,
                         "y":692
                        }, 
                        {
                         "x":124,
                         "y":420
                        }, 
                        {
                         "x":-52,
                         "y":216
                        }, 
                        {
                         "x":-12,
                         "y":0
                        }],
                 "properties":
                    {

                    },
                 "type":"Static",
                 "width":0,
                 "x":4560,
                 "y":2724
                }, 
                {
                 "height":0,
                 "name":"finalObstacle",
                 "polyline":[
                        {
                         "x":0,
                         "y":0
                        }, 
                        {
                         "x":192,
                         "y":192
                        }, 
                        {
                         "x":160,
                         "y":224
                        }, 
                        {
                         "x":-32,
                         "y":32
                        }, 
                        {
                         "x":0,
                         "y":0
                        }],
                 "properties":
                    {
                     "triggerMovement":"movement3",
                     "triggerMovementSpeed":"5"
                    },
                 "type":"Kinematic",
                 "width":0,
                 "x":4768,
                 "y":3584
                }, 
                {
                 "height":32,
                 "name":"rotMovement1",
                 "properties":
                    {
                     "angleFunction2":"3.14159 * Math.sin(0.05 * t)",
                     "angleFunction3":"t",
                     "wFunction":"1"
                    },
                 "type":"RotationMovement",
                 "width":32,
                 "x":5507,
                 "y":4449
                }, 
                {
                 "height":0,
                 "name":"finalObstacle",
                 "polyline":[
                        {
                         "x":0,
                         "y":0
                        }, 
                        {
                         "x":401,
                         "y":383
                        }, 
                        {
                         "x":369,
                         "y":415
                        }, 
                        {
                         "x":-32,
                         "y":32
                        }, 
                        {
                         "x":0,
                         "y":0
                        }],
                 "properties":
                    {
                     "centerObject":"rotMovement1",
                     "rotationMovement":"rotMovement1"
                    },
                 "type":"Kinematic",
                 "width":0,
                 "x":5135,
                 "y":4065
                }],
         "opacity":1,
         "type":"objectgroup",
         "visible":true,
         "width":200,
         "x":0,
         "y":0
        }, 
        {
         "height":200,
         "name":"SolidLayer",
         "objects":[
                {
                 "height":0,
                 "name":"",
                 "polygon":[
                        {
                         "x":-314,
                         "y":28
                        }, 
                        {
                         "x":467,
                         "y":13
                        }, 
                        {
                         "x":626,
                         "y":-44
                        }, 
                        {
                         "x":482,
                         "y":-111
                        }, 
                        {
                         "x":242,
                         "y":-131
                        }, 
                        {
                         "x":-313,
                         "y":-107
                        }],
                 "properties":
                    {

                    },
                 "type":"Static",
                 "width":0,
                 "x":2075,
                 "y":1472
                }, 
                {
                 "height":0,
                 "name":"",
                 "polygon":[
                        {
                         "x":0,
                         "y":0
                        }, 
                        {
                         "x":128,
                         "y":0
                        }, 
                        {
                         "x":128,
                         "y":32
                        }, 
                        {
                         "x":0,
                         "y":32
                        }],
                 "properties":
                    {
                     "periodicMovement":"movement1",
                     "periodicMovmenetSpeed":"2"
                    },
                 "type":"Kinematic",
                 "width":0,
                 "x":2545,
                 "y":1330
                }, 
                {
                 "height":0,
                 "name":"movement1",
                 "polyline":[
                        {
                         "x":0,
                         "y":0
                        }, 
                        {
                         "x":122,
                         "y":-179
                        }],
                 "properties":
                    {

                    },
                 "type":"Movement",
                 "width":0,
                 "x":2610,
                 "y":1343
                }, 
                {
                 "height":0,
                 "name":"",
                 "polygon":[
                        {
                         "x":0,
                         "y":0
                        }, 
                        {
                         "x":-82,
                         "y":85
                        }, 
                        {
                         "x":70,
                         "y":284
                        }, 
                        {
                         "x":337,
                         "y":31
                        }, 
                        {
                         "x":497,
                         "y":-129
                        }, 
                        {
                         "x":244,
                         "y":-184
                        }],
                 "properties":
                    {

                    },
                 "type":"Static",
                 "width":0,
                 "x":3023,
                 "y":1249
                }, 
                {
                 "height":0,
                 "name":"fourCorners",
                 "polygon":[
                        {
                         "x":32,
                         "y":-164
                        }, 
                        {
                         "x":-82,
                         "y":85
                        }, 
                        {
                         "x":138,
                         "y":114
                        }, 
                        {
                         "x":248,
                         "y":-151
                        }],
                 "properties":
                    {

                    },
                 "type":"Static",
                 "width":0,
                 "x":2681,
                 "y":1025
                }, 
                {
                 "height":0,
                 "name":"",
                 "polygon":[
                        {
                         "x":-156,
                         "y":26
                        }, 
                        {
                         "x":328,
                         "y":158
                        }, 
                        {
                         "x":813,
                         "y":167
                        }, 
                        {
                         "x":1135,
                         "y":86
                        }, 
                        {
                         "x":1259,
                         "y":179
                        }, 
                        {
                         "x":1547,
                         "y":147
                        }, 
                        {
                         "x":1569,
                         "y":444
                        }, 
                        {
                         "x":587,
                         "y":359
                        }, 
                        {
                         "x":-250,
                         "y":378
                        }],
                 "properties":
                    {

                    },
                 "type":"Static",
                 "width":0,
                 "x":1941,
                 "y":1581
                }, 
                {
                 "height":0,
                 "name":"movement2",
                 "polyline":[
                        {
                         "x":0,
                         "y":0
                        }, 
                        {
                         "x":-4,
                         "y":256
                        }],
                 "properties":
                    {

                    },
                 "type":"Movement",
                 "width":0,
                 "x":3097,
                 "y":1617
                }, 
                {
                 "height":0,
                 "name":"door",
                 "polygon":[
                        {
                         "x":2,
                         "y":-26
                        }, 
                        {
                         "x":4,
                         "y":-214
                        }, 
                        {
                         "x":-28,
                         "y":-214
                        }, 
                        {
                         "x":-30,
                         "y":-26
                        }],
                 "properties":
                    {
                     "triggerMovement":"movement2",
                     "triggerMovementSpeed":"4"
                    },
                 "type":"Kinematic",
                 "width":0,
                 "x":3116,
                 "y":1715
                }, 
                {
                 "height":0,
                 "name":"",
                 "polyline":[
                        {
                         "x":64,
                         "y":-93
                        }, 
                        {
                         "x":160,
                         "y":219
                        }, 
                        {
                         "x":-1,
                         "y":482
                        }, 
                        {
                         "x":197,
                         "y":748
                        }, 
                        {
                         "x":330,
                         "y":239
                        }, 
                        {
                         "x":245,
                         "y":-173
                        }, 
                        {
                         "x":128,
                         "y":-192
                        }, 
                        {
                         "x":64,
                         "y":-93
                        }],
                 "properties":
                    {

                    },
                 "type":"Static",
                 "width":0,
                 "x":3808,
                 "y":1056
                }, 
                {
                 "height":0,
                 "name":"movement3",
                 "polyline":[
                        {
                         "x":0,
                         "y":0
                        }, 
                        {
                         "x":262,
                         "y":296
                        }],
                 "properties":
                    {

                    },
                 "type":"Movement",
                 "width":0,
                 "x":4922,
                 "y":3768
                }],
         "opacity":1,
         "type":"objectgroup",
         "visible":true,
         "width":200,
         "x":0,
         "y":0
        }, 
        {
         "height":200,
         "name":"ObjectsLayer",
         "objects":[
                {
                 "height":55,
                 "name":"player",
                 "properties":
                    {
                     "directionLine":"dir"
                    },
                 "type":"Player",
                 "width":58,
                 "x":4880,
                 "y":2284
                }, 
                {
                 "height":56,
                 "name":"",
                 "properties":
                    {
                     "behaviorName":"patrolAttack",
                     "defensiveLevel":"5",
                     "guardAreas":"guardArea1 guardArea2 guardArea3 guardArea4",
                     "manouverLevel":"20",
                     "offensiveLevel":"5",
                     "priority":"2",
                     "triggerIntenseMusic":"true",
                     "vehicle":"enemy_1"
                    },
                 "type":"Enemy",
                 "width":57,
                 "x":3697,
                 "y":1293
                }, 
                {
                 "height":86,
                 "name":"",
                 "properties":
                    {
                     "active":"true",
                     "triggerObjects":"door"
                    },
                 "type":"Trigger",
                 "width":90,
                 "x":2345,
                 "y":1571
                }, 
                {
                 "height":56,
                 "name":"",
                 "properties":
                    {
                     "defensiveLevel":"5",
                     "guardAreas":"guardArea1 guardArea2 guardArea3 guardArea4",
                     "manouverLevel":"20",
                     "offensiveLevel":"5",
                     "priority":"1",
                     "vehicle":"enemy_1"
                    },
                 "type":"Enemy",
                 "width":57,
                 "x":1365,
                 "y":609
                }, 
                {
                 "height":56,
                 "name":"",
                 "properties":
                    {
                     "angle":"0.5",
                     "behaviorName":"patrolAttack",
                     "defensiveLevel":"5",
                     "guardAreas":"guardArea5",
                     "manouverLevel":"20",
                     "offensiveLevel":"5",
                     "planningGraph":"big",
                     "priority":"10",
                     "vehicle":"enemy_2"
                    },
                 "type":"Enemy",
                 "width":57,
                 "x":5671,
                 "y":861
                }, 
                {
                 "height":56,
                 "name":"",
                 "properties":
                    {
                     "defensiveLevel":"5",
                     "destroyMessage":"WELL DONE!",
                     "destroyMessageType":"screen",
                     "destroyReward":"cfReward",
                     "guardAreas":"guardArea1 guardArea2 guardArea3 guardArea4",
                     "manouverLevel":"20",
                     "offensiveLevel":"5",
                     "priority":"3",
                     "vehicle":"enemy_1"
                    },
                 "type":"Enemy",
                 "width":57,
                 "x":2321,
                 "y":2335
                }, 
                {
                 "height":109,
                 "name":"cp1",
                 "properties":
                    {
                     "active":"true",
                     "next":"cp2"
                    },
                 "type":"Checkpoint",
                 "width":107,
                 "x":3159,
                 "y":2140
                }, 
                {
                 "height":109,
                 "name":"cp2",
                 "properties":
                    {
                     "active":"false",
                     "next":"cp3"
                    },
                 "type":"Checkpoint",
                 "width":107,
                 "x":1537,
                 "y":1576
                }, 
                {
                 "height":109,
                 "name":"cp3",
                 "properties":
                    {
                     "active":"false",
                     "next":"cp4"
                    },
                 "type":"Checkpoint",
                 "width":107,
                 "x":2601,
                 "y":1180
                }, 
                {
                 "height":109,
                 "name":"cp4",
                 "properties":
                    {
                     "active":"false",
                     "next":"cp5"
                    },
                 "type":"Checkpoint",
                 "width":107,
                 "x":3785,
                 "y":1946
                }, 
                {
                 "height":109,
                 "name":"cp5",
                 "properties":
                    {
                     "active":"false",
                     "next":"cp6",
                     "triggerObjects":"finalObstacle"
                    },
                 "type":"Checkpoint",
                 "width":107,
                 "x":4625,
                 "y":2862
                }, 
                {
                 "height":109,
                 "name":"cp6",
                 "properties":
                    {
                     "active":"false",
                     "isGoal":"true"
                    },
                 "type":"Checkpoint",
                 "width":107,
                 "x":4579,
                 "y":3328
                }],
         "opacity":1,
         "type":"objectgroup",
         "visible":true,
         "width":200,
         "x":0,
         "y":0
        }, 
        {
         "height":200,
         "name":"BackgroundLayer",
         "objects":[
                {
                 "height":64,
                 "name":"planet1",
                 "properties":
                    {
                     "latSteps":"15",
                     "lonSteps":"10",
                     "r":"100",
                     "type":"planet",
                     "x":"200",
                     "y":"-300",
                     "z":"-400"
                    },
                 "type":"BackgroundObject",
                 "width":64,
                 "x":1881,
                 "y":300
                }, 
                {
                 "height":64,
                 "name":"stuff1",
                 "properties":
                    {
                     "csg1":"CSG.torus({ radius1: 60, radius2: 15, stacks: 8, slices: 8 })",
                     "csg2":"CSG.cylinder({radius:12, start: [-55, 0, 0], end: [55, 0, 0], slices: 5})",
                     "csg3":"CSG.cylinder({radius:12, start: [0, -55, 0], end: [0, 55, 0], slices: 5})",
                     "result":"csg1.union(csg2).union(csg3)",
                     "type":"csg",
                     "upX":"0.5",
                     "upY":"0.5",
                     "upZ":"2",
                     "x":"0",
                     "y":"-100",
                     "z":"-100"
                    },
                 "type":"BackgroundObject",
                 "width":64,
                 "x":2287,
                 "y":238
                }],
         "opacity":1,
         "type":"objectgroup",
         "visible":true,
         "width":200,
         "x":0,
         "y":0
        }, 
        {
         "height":200,
         "name":"ForegroundLayer",
         "objects":[],
         "opacity":1,
         "type":"objectgroup",
         "visible":true,
         "width":200,
         "x":0,
         "y":0
        }],
 "orientation":"orthogonal",
 "properties":
    {
     "background":"0",
     "completeScore":"100",
     "gravity":"0,0",
     "levelsCompletedRequired":"",
     "levelsUnlockedRequired":"",
     "music":"0",
     "name":"Flight Test",
     "scoreRequired":"0",
     "unlockLevels":"",
     "upgradesRequired":"0",
     "zoom":"1"
    },
 "tileheight":32,
 "tilesets":[],
 "tilewidth":32,
 "version":1,
 "width":200
}